taisim2/__init__.py
taisim2/input_handler.py
taisim2/logging_system.py
taisim2/robot.py
taisim2/sensors.py
taisim2/simulator.py
taisim2/utils.py
taisim2/data/Cropps1.png
taisim2/data/Cropps2.png
taisim2/data/LaneKeeper1.png
taisim2/data/LaneKeeper2.png
taisim2/data/LaneKeeper3.png
taisim2/data/LineFollower1.png
taisim2/data/LineFollower2.png
taisim2-0.1.6.dist-info/LICENSE
taisim2-0.1.6.dist-info/METADATA
taisim2-0.1.6.dist-info/WHEEL
taisim2-0.1.6.dist-info/entry_points.txt
taisim2-0.1.6.dist-info/top_level.txt
taisim2-0.1.6.dist-info/RECORD
